apptemplates/__init__.py
apptemplates/test/__init__.py
apptemplates/test/settings.py
apptemplates/test/urls.py
django_apptemplates-1.5.dist-info/DESCRIPTION.rst
django_apptemplates-1.5.dist-info/METADATA
django_apptemplates-1.5.dist-info/RECORD
django_apptemplates-1.5.dist-info/WHEEL
django_apptemplates-1.5.dist-info/metadata.json
django_apptemplates-1.5.dist-info/top_level.txt
